ayaka_db/__init__.py
ayaka_db/database.py
ayaka_db-0.0.3.dist-info/METADATA
ayaka_db-0.0.3.dist-info/WHEEL
ayaka_db-0.0.3.dist-info/RECORD
