Metadata-Version: 2.1
Name: ayaka-db
Version: 0.0.3
Summary: 
Home-page: https://github.com/bridgeL/ayaka_db
Author: Su
Author-email: wxlxy316@163.com
Requires-Python: >=3.10,<4.0
Classifier: Programming Language :: Python :: 3
Classifier: Programming Language :: Python :: 3.10
Classifier: Programming Language :: Python :: 3.11
Requires-Dist: ayaka_utils (>=0.0.3)
Requires-Dist: inflection (>=0.5.1)
Requires-Dist: loguru (>=0.6.0)
Requires-Dist: sqlmodel (>=0.0.8)
Project-URL: Repository, https://github.com/bridgeL/ayaka_db
